pubmedtool/__init__.py
pubmedtool/pubmed_fetcher.py
pubmedtool-0.1.3.dist-info/LICENSE
pubmedtool-0.1.3.dist-info/METADATA
pubmedtool-0.1.3.dist-info/WHEEL
pubmedtool-0.1.3.dist-info/entry_points.txt
pubmedtool-0.1.3.dist-info/RECORD
