Metadata-Version: 2.3
Name: pubmedtool
Version: 0.1.3
Summary: A tool to get papers list from pubmed
Author: Pushpender
Author-email: pushpenderjangra2005@gmail.com
Requires-Python: >=3.10
Classifier: Programming Language :: Python :: 3
Classifier: Programming Language :: Python :: 3.10
Classifier: Programming Language :: Python :: 3.11
Classifier: Programming Language :: Python :: 3.12
Classifier: Programming Language :: Python :: 3.13
Requires-Dist: requests (>=2.32.3,<3.0.0)
